common_fsm/__init__.py
common_fsm/async_fsm.py
common_fsm/fsm.py
common_fsm-0.1.3.dist-info/METADATA
common_fsm-0.1.3.dist-info/WHEEL
common_fsm-0.1.3.dist-info/licenses/LICENSE
common_fsm-0.1.3.dist-info/RECORD
