Metadata-Version: 2.4
Name: common-fsm
Version: 0.1.3
Summary: A simple and flexible Finite State Machine implementation in Python
Project-URL: Homepage, https://github.com/commonai/python-fsm
Project-URL: Bug Tracker, https://github.com/commonai/python-fsm/issues
Project-URL: Source Code, https://github.com/commonai/python-fsm
Author-email: Helge Modén <helgemod@gmail.com>
License: MIT License
License-File: LICENSE
Keywords: async,finite-state-machine,fsm,python,state-machine
Classifier: Development Status :: 4 - Beta
Classifier: Intended Audience :: Developers
Classifier: License :: OSI Approved :: MIT License
Classifier: Operating System :: OS Independent
Classifier: Programming Language :: Python :: 3
Classifier: Programming Language :: Python :: 3.7
Classifier: Programming Language :: Python :: 3.8
Classifier: Programming Language :: Python :: 3.9
Classifier: Programming Language :: Python :: 3.10
Classifier: Programming Language :: Python :: 3.11
Classifier: Programming Language :: Python :: 3.12
Classifier: Topic :: Software Development :: Libraries :: Python Modules
Requires-Python: >=3.7
Provides-Extra: dev
Requires-Dist: black; extra == 'dev'
Requires-Dist: flake8; extra == 'dev'
Requires-Dist: mypy; extra == 'dev'
Requires-Dist: pytest>=6.0; extra == 'dev'
